{
	"1": "20nov1st",
	"10": "celebsub",
	"1001": "588",
	"1002": "1samurai",
	"1003": "a_jax",
	"1004": "atemple",
	"1005": "astral",
	"1006": "babylove",
	"1007": "backinto",
	"1009": "boundary",
	"101": "brill2u",
	"1010": "carryon",
	"1012": "choochoo",
	"1013": "cosmic",
	"1014": "daisuke",
	"1015": "debtty",
	"1016": "desolat",
	"101643": "thund28r",
	"101644": "tpolak30",
	"1017": "doll",
	"1018": "dontfgt",
	"1019": "dropflr",
	"102": "deepin",
	"1020": "exe",
	"1021": "feedback",
	"102154": "cleopatr",
	"1022": "feelit",
	"1023": "freezing",
	"1024": "ghost",
	"1025": "grafull",
	"1026": "hischdrm",
	"102666": "smoooosh",
	"1027": "high",
	"1028": "innocent",
	"102867": "_sakazki",
	"102868": "2beasts",
	"1029": "jam",
	"103": "deepindd",
	"1030": "letsrun",
	"1031": "limited",
	"1032": "loveter",
	"1034": "low",
	"1035": "lucy",
	"1036": "narciss",
	"1037": "nodoubt",
	"1038": "no13",
	"1039": "onemore",
	"104": "genom",
	"1040": "pandora",
	"104060": "_uen",
	"1041": "platxxx",
	"1042": "r2",
	"1043": "rbwrbw",
	"1044": "rockit",
	"1045": "risendjt",
	"1046": "risen",
	"1047": "scherzo",
	"1048": "score",
	"1049": "shakin31",
	"1050": "shotstar",
	"1051": "smell",
	"1052": "spfight",
	"1053": "thinkof",
	"1054": "_sysroma",
	"1055": "_donna",
	"1056": "_ichizu",
	"1057": "_stge_cs",
	"1058": "_stgekka",
	"1059": "rockit_t",
	"1060": "score29",
	"107": "gentle",
	"108": "keepon",
	"109": "keepon15",
	"1091": "drmngdrm",
	"1092": "swingmyw",
	"1093": "_cmflg",
	"1094": "alwayswe",
	"1095": "vo_id",
	"1096": "mathe_gb",
	"1097": "stylus",
	"1098": "shamshir",
	"1099": "_wakloli",
	"11": "celeb",
	"110": "macho",
	"1101": "aa_amuro",
	"1102": "ageha",
	"1103": "andromed",
	"1104": "awaken",
	"1105": "backflr",
	"1106": "bequiet",
	"1107": "believe_",
	"1108": "blocks",
	"1109": "breath",
	"111": "nahanaha",
	"1110": "cardream",
	"1111": "click",
	"1112": "closeyes",
	"1113": "dance_",
	"1114": "d_afraid",
	"1115": "earthscp",
	"1116": "evo66",
	"1117": "faketime",
	"1118": "flyindia",
	"1119": "genocide",
	"112": "paramax",
	"1120": "gigadel",
	"1121": "harmony",
	"1122": "horizon",
	"1123": "inject",
	"1124": "kecak",
	"1125": "key",
	"1126": "kiseki",
	"1127": "kingrove",
	"1128": "lesfill",
	"1129": "listento",
	"113": "rugged",
	"1130": "moremove",
	"1131": "moveme",
	"1132": "nebula_c",
	"1133": "nebula",
	"1134": "nitokyo",
	"1135": "on_tube",
	"1136": "perworld",
	"1137": "raspbery",
	"1138": "redzone",
	"1139": "reso1794",
	"114": "theearth",
	"1140": "rokworld",
	"1141": "seclove",
	"1142": "spdy_cat",
	"1143": "sphere",
	"1144": "spiral",
	"1145": "tellme",
	"1146": "texture",
	"1147": "thehoped",
	"1148": "thehope",
	"1149": "ultimate",
	"1150": "wonbull",
	"1151": "_psasori",
	"1152": "_taiyo",
	"1153": "_oosan",
	"1154": "_perplex",
	"1157": "nebula_g",
	"116": "_chotto",
	"118": "gentle27",
	"12": "deepeyes",
	"1201": "100mnm_g",
	"1202": "agnusdei",
	"1203": "alturca",
	"1204": "aurora",
	"1205": "captive",
	"1206": "catchme",
	"1207": "dntletit",
	"1208": "dbthrash",
	"1209": "eden",
	"1210": "emptysky",
	"1211": "fst_reso",
	"1212": "funktion",
	"1213": "gardenhs",
	"1214": "getemup",
	"1215": "greeneye",
	"1216": "hp_angel",
	"1217": "i_am",
	"1218": "inmotion",
	"1219": "inazuma",
	"1220": "lesson5",
	"1221": "listenup",
	"1222": "littlepr",
	"1223": "lvmagic",
	"1224": "mind_gap",
	"1225": "moonrace",
	"1226": "patriot",
	"1227": "pinkr_ra",
	"1229": "plasma",
	"1230": "pollino",
	"1231": "poodle",
	"1232": "rageagst",
	"1233": "sc_squad",
	"1234": "script_a",
	"1235": "script_h",
	"1236": "script_l",
	"1237": "script_n",
	"1238": "scripted",
	"1239": "sexysexy",
	"1240": "sigsig",
	"1241": "spark",
	"1242": "tant_pis",
	"1243": "tizona",
	"1244": "toejam",
	"1245": "twelfth",
	"1246": "undersky",
	"1247": "vault",
	"1248": "votum",
	"1249": "we_disco",
	"1250": "xepher",
	"1251": "_orebeat",
	"1252": "_tissue",
	"1253": "_hima_gd",
	"1254": "_hima_cs",
	"1255": "_rakuen",
	"1256": "_gekkou",
	"1257": "_tsj_ryu",
	"1258": "_mei",
	"1261": "dntlet28",
	"1262": "mindgp29",
	"13": "dvmny_gd",
	"1301": "alfar",
	"1302": "apocalps",
	"1303": "ay_crmba",
	"1304": "balfeath",
	"1305": "bloody_t",
	"1306": "bluemoon",
	"1307": "boomdisc",
	"1308": "breakout",
	"1309": "brdband",
	"1310": "concert",
	"1312": "contract",
	"1313": "crz_kino",
	"1314": "dcfish",
	"1315": "deeproar",
	"1316": "dbloving",
	"1317": "due_tmrw",
	"1318": "enjoy_yl",
	"1319": "euroman",
	"1320": "ganymede",
	"1321": "harmlove",
	"1322": "hvnlysun",
	"1323": "ifuture",
	"1324": "inferno",
	"1325": "leaving",
	"1326": "looksky",
	"1327": "melolife",
	"1328": "mint",
	"1329": "moon",
	"1330": "parasite",
	"1331": "power_lv",
	"1332": "pre_puni",
	"1333": "samba_de",
	"1334": "so_fabul",
	"1335": "spr_rain",
	"1336": "sunfield",
	"1337": "thedirty",
	"1338": "thisislv",
	"1339": "tgyamato",
	"1340": "tonight",
	"1341": "trip_mc",
	"1342": "tripping",
	"1343": "typemars",
	"1344": "ubiquits",
	"1345": "waxing",
	"1346": "whydidyu",
	"1347": "win11_9",
	"1348": "wisheuro",
	"1349": "wish",
	"1350": "withyou",
	"1351": "zenius",
	"1352": "_kagono",
	"1353": "_tashika",
	"1354": "_kachofu",
	"1355": "_nageki",
	"1356": "_nijiiro",
	"1357": "_wana",
	"1358": "leavingt",
	"1361": "dproar30",
	"14": "dvmoney",
	"1401": "2hot2eat",
	"1402": "airbell",
	"1403": "andro2",
	"1404": "blindjus",
	"1405": "candygal",
	"1406": "c_sabaki",
	"1407": "c_chikai",
	"1408": "comeon",
	"1409": "crosroad",
	"1410": "cybforce",
	"1411": "drmsweet",
	"1412": "eth_like",
	"1413": "fas_maxx",
	"1414": "firefire",
	"1415": "fourleaf",
	"1416": "gbusters",
	"1417": "goldrush",
	"1418": "g_knight",
	"1419": "halfmoon",
	"1420": "hvnabove",
	"1421": "hs_love",
	"1422": "hnypunch",
	"1423": "inori",
	"1425": "kmitachi",
	"1426": "lcruster",
	"1427": "lvagain_",
	"1428": "make_myo",
	"1429": "mtl_mind",
	"1430": "myonly",
	"1431": "never_",
	"1432": "op31jojo",
	"1433": "photon_g",
	"1435": "playback",
	"1436": "rrrising",
	"1437": "roulette",
	"1438": "secondhv",
	"1439": "sens2007",
	"1440": "smile",
	"1441": "snwstorm",
	"1442": "soreal",
	"1443": "stars_rt",
	"1444": "t_shadow",
	"1445": "thesmile",
	"1446": "tranoid",
	"1447": "vanessa",
	"1449": "watchout",
	"1450": "wy_smile",
	"1451": "x_rated",
	"1452": "yabis_sl",
	"1453": "_camiro",
	"1454": "_curulab",
	"1455": "_ctangel",
	"1456": "_yoshida",
	"1457": "_regret",
	"1458": "_hanafbk",
	"1459": "_kgonshu",
	"1460": "_ninelem",
	"1461": "_fattack",
	"1462": "_zero",
	"1463": "gknightt",
	"15": "doyulvme",
	"1501": "ubertref",
	"1502": "2tribe4k",
	"1503": "anisakis",
	"1504": "a_guerre",
	"1505": "be_ok",
	"1506": "beatonic",
	"1507": "bluerain",
	"1508": "darmyluv",
	"1509": "dazzlin",
	"1510": "digitank",
	"1511": "kickout",
	"1512": "doit_emp",
	"1514": "endworld",
	"1515": "evrgreen",
	"1516": "fourpces",
	"1517": "freeway",
	"1518": "im4ctaka",
	"1519": "icarus",
	"1520": "inthesky",
	"1521": "journey2",
	"1522": "lvlystrm",
	"1523": "mdrugada",
	"1524": "maxlove",
	"1525": "mendes",
	"1526": "meltdown",
	"1527": "new_gene",
	"1528": "now4ever",
	"1529": "oratio",
	"1530": "pr_hades",
	"1531": "pro4life",
	"1532": "radius",
	"1533": "reminis",
	"1534": "risinsun",
	"1535": "ristacia",
	"1536": "rokmenow",
	"1537": "sa2712ac",
	"1539": "satfinal",
	"1540": "scar_eth",
	"1541": "shadesof",
	"1542": "shift",
	"1543": "solwaltz",
	"1544": "sgiallar",
	"1545": "sotart",
	"1546": "stneedle",
	"1547": "switch15",
	"1548": "tdeepstr",
	"1549": "trigger",
	"1550": "time2air",
	"1551": "triphnix",
	"1552": "troopers",
	"1553": "wn_party",
	"1554": "_eco_g",
	"1555": "_s_machi",
	"1556": "_m_resid",
	"1557": "_hranman",
	"1558": "_kanau",
	"1559": "_kokodo",
	"1560": "_kid_a",
	"1561": "_shonan",
	"1562": "_thelast",
	"1563": "2tribelc",
	"1564": "sotart24",
	"1568": "mdrugd25",
	"1570": "triphx26",
	"1572": "solwlz27",
	"1573": "risins27",
	"16": "drlove",
	"1601": "3y3s",
	"1602": "allineed",
	"1603": "almyturn",
	"1604": "arabian",
	"1605": "bemani4u",
	"1606": "bahram",
	"1607": "bitchoco",
	"1608": "bridal_f",
	"1609": "ckakusei",
	"1610": "cocookie",
	"1611": "cyber_4c",
	"1612": "punch_lv",
	"1613": "fback90s",
	"1614": "flyabove",
	"1615": "gobeyond",
	"1616": "house_na",
	"1617": "hyperion",
	"1618": "imscream",
	"1619": "jack",
	"1620": "jewelstm",
	"1621": "jalsmile",
	"1622": "kung_fu",
	"1623": "marieant",
	"1624": "mmapping",
	"1625": "monkey09",
	"1626": "myfuture",
	"1627": "naughty",
	"1628": "neogenes",
	"1629": "no_crime",
	"1630": "our_song",
	"1631": "prgworld",
	"1632": "psychegt",
	"1633": "qtragedy",
	"1634": "secrets",
	"1635": "smooooch",
	"1636": "sltn_emp",
	"1638": "thank_u4",
	"1639": "tspola_k",
	"1640": "thund_hn",
	"1641": "turii",
	"1642": "v2_taka",
	"1643": "y_co_doa",
	"1644": "youllnow",
	"1645": "_atk_no3",
	"1646": "_haritya",
	"1647": "_mhoroba",
	"1648": "_mdatenc",
	"1649": "_ay_quiz",
	"1650": "_tkotome",
	"1651": "_rage16",
	"1652": "_himiko",
	"1653": "_fuchin",
	"1654": "_tsubasa",
	"1655": "_rintost",
	"1656": "_mdatn24",
	"1660": "ycodoa25",
	"17": "emo1st",
	"1701": "airraid",
	"1702": "almag_ra",
	"1704": "bmaniacs",
	"1705": "bas2bass",
	"1706": "beatchic",
	"1707": "btyangel",
	"1708": "beintorn",
	"1709": "bloominf",
	"1710": "brazfire",
	"1711": "c_sbk_ra",
	"1712": "c_sbk_r",
	"1713": "chocodan",
	"1714": "d_eagle",
	"1715": "dawn_end",
	"1716": "dazzlinr",
	"1717": "denjinsf",
	"1718": "desire",
	"1719": "doback",
	"1720": "dominion",
	"1721": "drop",
	"1722": "elisha",
	"1723": "empstate",
	"1724": "ephantom",
	"1725": "evans",
	"1726": "exusia",
	"1727": "g59",
	"1728": "galgalim",
	"1729": "goldcros",
	"1730": "hydrblue",
	"1731": "inthname",
	"1732": "keep_it",
	"1733": "lastburn",
	"1734": "litshine",
	"1735": "london",
	"1736": "miraclem",
	"1737": "miru_key",
	"1738": "mosaic",
	"1739": "mys_time",
	"1740": "new_sens",
	"1741": "nfiction",
	"1742": "one_kind",
	"1743": "prog_sun",
	"1744": "quell",
	"1745": "raison",
	"1746": "red_fmj",
	"1747": "rootsof",
	"1748": "session1",
	"1749": "she_wife",
	"1750": "sssquad",
	"1751": "sorrows",
	"1752": "spark_r",
	"1753": "special1",
	"1754": "spiral_r",
	"1755": "sunrise",
	"1756": "tlaststr",
	"1757": "thestory",
	"1758": "tofuture",
	"1759": "withme_",
	"1760": "_kzasobi",
	"1761": "_cosmos",
	"1762": "_sheaven",
	"1763": "_takara",
	"1764": "_babylon",
	"1765": "_fetish",
	"1766": "_valse17",
	"1767": "_suijo17",
	"1768": "_suijo",
	"1769": "_prismof",
	"1770": "almag_h",
	"1773": "doback29",
	"1790": "_kichika",
	"1791": "adventin",
	"1792": "ghosthmj",
	"1793": "smawedge",
	"1794": "eroica",
	"1795": "jetwindy",
	"1796": "dans_la",
	"18": "emo1stus",
	"1801": "aegis",
	"1802": "albida",
	"1803": "answer",
	"1804": "anthemld",
	"1805": "believme",
	"1806": "blstwind",
	"1807": "bouncex3",
	"1808": "brground",
	"1809": "brkneden",
	"1810": "cansei",
	"1811": "dancwith",
	"1812": "ddreamer",
	"1813": "dstsword",
	"1814": "dm_star",
	"1815": "emassive",
	"1816": "engdrive",
	"1817": "etntears",
	"1818": "evresort",
	"1819": "extrema2",
	"1820": "fantasia",
	"1821": "getout",
	"1822": "gldpalms",
	"1823": "hc_mania",
	"1824": "ifightme",
	"1825": "kailua",
	"1826": "la_mar",
	"1827": "lettrack",
	"1828": "life_scr",
	"1829": "love_km",
	"1830": "medilove",
	"1831": "mermaid",
	"1832": "nvrfade",
	"1833": "nwcastle",
	"1834": "paralost",
	"1835": "passfate",
	"1836": "perditus",
	"1837": "proglife",
	"1838": "prog_xac",
	"1839": "raisehnd",
	"1840": "reunion",
	"1841": "rokhouse",
	"1842": "saberwng",
	"1843": "sakurast",
	"1844": "session9",
	"1845": "space_tm",
	"1846": "stayside",
	"1847": "stellar",
	"1848": "takemehi",
	"1849": "tbknight",
	"1850": "thedoor",
	"1851": "tropical",
	"1852": "vmillion",
	"1853": "watchpt2",
	"1854": "weshonan",
	"1855": "wise_up",
	"1856": "xanadu_2",
	"1857": "youwere1",
	"1858": "zeta",
	"1859": "_o_koede",
	"1860": "_kagenui",
	"1861": "_rakuenr",
	"1862": "_krokami",
	"1863": "_shakunt",
	"1864": "_yuuyake",
	"1865": "_t_rerun",
	"1866": "_love21",
	"1867": "_chinaex",
	"1869": "wuv_u",
	"1870": "surgames",
	"1871": "sakurarf",
	"1872": "ssc",
	"1873": "t_fallen",
	"1874": "brokenrb",
	"1875": "kailua_h",
	"1877": "nwcasl26",
	"1891": "matsuri",
	"1892": "movewekp",
	"1893": "likevamp",
	"1894": "_spbaban",
	"1895": "globeglt",
	"1896": "dualstr",
	"19": "gmd_us",
	"1901": "a_minstr",
	"1902": "almace",
	"1903": "anagrams",
	"1904": "blackbyx",
	"1905": "call",
	"1906": "change_w",
	"1907": "dontwake",
	"1908": "driveme",
	"1909": "ehighway",
	"1910": "evlution",
	"1911": "exmotion",
	"1912": "f_amuro",
	"1913": "fareast",
	"1914": "follow_t",
	"1915": "gigant",
	"1916": "im_happy",
	"1917": "into_sun",
	"1918": "kyamsama",
	"1919": "lax5",
	"1920": "lcrystal",
	"1921": "love_bbb",
	"1922": "luckyday",
	"1923": "mermaidr",
	"1924": "miamisun",
	"1925": "phoenix",
	"1926": "prompt",
	"1927": "q_silver",
	"1928": "releasem",
	"1929": "roundx2",
	"1930": "sesion12",
	"1931": "several",
	"1932": "snwgoose",
	"1933": "strtrail",
	"1934": "thunbolt",
	"1935": "voxane",
	"1936": "yellow_s",
	"1937": "24th_boy",
	"1938": "_kagachi",
	"1939": "_kagerou",
	"1940": "_klockon",
	"1941": "_koisuru",
	"1942": "_suishok",
	"1943": "_ymir",
	"1944": "shade",
	"1945": "diavolo",
	"1946": "penta_cb",
	"1947": "inf_cave",
	"1948": "quantum",
	"1949": "fffff",
	"1950": "_kodomo",
	"1951": "snakestk",
	"1952": "synrstar",
	"1953": "trust2dx",
	"1954": "w_walker",
	"1955": "yheadjoe",
	"1956": "_rovknee",
	"1957": "resistan",
	"1958": "lethbolg",
	"1959": "532nm",
	"1960": "_bt_rcpt",
	"1961": "flipflap",
	"1962": "csl_moon",
	"1963": "titans",
	"1964": "quaver",
	"1965": "haeretic",
	"1991": "t_sample",
	"1992": "scharfri",
	"1993": "in_black",
	"1994": "_seijin",
	"1995": "todestri",
	"1996": "nnrt",
	"1997": "thelimbo",
	"1998": "yaksha",
	"1999": "_tkyoake",
	"2": "511",
	"20": "gmd",
	"2001": "ascalon",
	"2002": "blue_str",
	"2003": "brk_dawn",
	"2004": "connectv",
	"2005": "deceive",
	"2006": "devilz_s",
	"2007": "echo_of",
	"2008": "flower",
	"2009": "flyyouto",
	"201": "_59",
	"2010": "gra2012",
	"2011": "howling",
	"2012": "ikwyoukw",
	"2013": "ilias",
	"2014": "illegal",
	"2015": "inheaven",
	"2016": "liberatn",
	"2017": "lt_cyber",
	"2018": "ltl_star",
	"2019": "luvsaveu",
	"2020": "neonlits",
	"2021": "point_0",
	"2022": "portal",
	"2023": "praludim",
	"2024": "re_gene",
	"2025": "shnworld",
	"2026": "spinning",
	"2027": "takelife",
	"2028": "tomystar",
	"2029": "ylw_frog",
	"203": "badboy3",
	"2030": "zed",
	"2031": "405nm",
	"2032": "_kagenno",
	"2033": "_kuruizk",
	"2034": "_meimetu",
	"2035": "soljob2",
	"2036": "sync_ant",
	"2037": "_elpis",
	"2038": "rumrum",
	"2039": "sick",
	"204": "badboy",
	"2040": "concept",
	"2041": "thors_hm",
	"2042": "nwdecade",
	"2043": "plan8",
	"2044": "neu",
	"2045": "holywood",
	"2046": "jomanda",
	"2047": "_travels",
	"2048": "8bit_pri",
	"2049": "_trikago",
	"205": "brazil",
	"2050": "planaria",
	"2051": "_decoher",
	"2052": "tp_rz",
	"2053": "proof_of",
	"2054": "daydream",
	"2055": "tpiece_2",
	"2056": "tpiececn",
	"2057": "rbwafter",
	"2058": "beastie",
	"2059": "_astraia",
	"206": "dancin",
	"2060": "_nagisa",
	"2061": "holysnow",
	"2062": "trueblue",
	"2063": "confiser",
	"2064": "bravglow",
	"2065": "vega",
	"2066": "_casino",
	"2067": "newlight",
	"2068": "fractal",
	"2069": "_sokseki",
	"207": "digital",
	"2070": "_njihana",
	"2071": "_howrice",
	"2072": "_rakirak",
	"2073": "gaia",
	"2074": "stulti",
	"2075": "empatic",
	"2076": "synergy",
	"2077": "_seiten",
	"2078": "_gennote",
	"2079": "elecreat",
	"208": "dongtepo",
	"2080": "_kyatora",
	"2081": "shion",
	"2082": "_ongaku",
	"2083": "_oboro",
	"2084": "_schrcat",
	"2085": "_umeyuki",
	"2086": "exaleave",
	"2087": "vallis",
	"2088": "valanga",
	"2089": "zirkfied",
	"209": "eletune",
	"21": "gmd3a",
	"210": "getonbt",
	"2101": "adularia",
	"2102": "alba",
	"2103": "atropos",
	"2104": "ccrystal",
	"2105": "darklgcy",
	"2106": "dvl_sacr",
	"2107": "diagram",
	"2108": "euphoria",
	"2109": "elespada",
	"211": "headache",
	"2110": "esrever",
	"2111": "extrmach",
	"2112": "funnysfl",
	"2113": "giveyrlv",
	"2114": "insanetc",
	"2115": "insomnia",
	"2116": "lafesta",
	"2117": "ltshower",
	"2118": "m1dy_dx",
	"2119": "madatack",
	"212": "hitch1",
	"2120": "magic_lv",
	"2121": "miracle5",
	"2122": "npcworld",
	"2123": "odin",
	"2124": "overload",
	"2125": "rbguitar",
	"2126": "rise",
	"2127": "valgus",
	"2128": "wobbleip",
	"2129": "wndrgirl",
	"213": "iwasonec",
	"2130": "_aigipan",
	"2131": "_cholove",
	"2132": "_s_dogma",
	"2133": "_tsumito",
	"2134": "_twenty",
	"2135": "closewld",
	"2136": "punisher",
	"2137": "sinistra",
	"2138": "_mind_gm",
	"2139": "hyena",
	"214": "iwasone",
	"2140": "_oneinst",
	"2141": "pharaoh",
	"2142": "raam",
	"2143": "sigmund",
	"2144": "_deadbal",
	"2145": "squeeze",
	"2146": "_howbase",
	"2147": "_todorok",
	"2148": "engraved",
	"2149": "ancients",
	"215": "iminlove",
	"2150": "nemesisp",
	"2151": "votumhmj",
	"2152": "darkfall",
	"2153": "bldragon",
	"2154": "hypsonik",
	"2155": "refindex",
	"2156": "lstdance",
	"2157": "_nine_ix",
	"2158": "invoker",
	"2159": "_alstroe",
	"216": "indigo",
	"2160": "_aether",
	"2161": "smugface",
	"2162": "iwilback",
	"2163": "feelbeat",
	"2168": "_momoka",
	"2169": "allwreck",
	"217": "junglong",
	"2170": "shatterd",
	"2171": "intobtlf",
	"2172": "braveout",
	"2173": "immortal",
	"2174": "mdinject",
	"2175": "_elefthe",
	"2176": "_ltspeed",
	"2177": "verflcht",
	"2178": "_bamboos",
	"2179": "_gensouk",
	"218": "junglist",
	"2180": "idola",
	"2181": "schwarzs",
	"2182": "kaiserph",
	"2183": "_wadatmi",
	"2185": "_osenju",
	"2186": "khamenbr",
	"2187": "rise_pd",
	"219": "letbtem",
	"22": "gambol",
	"220": "lovinyou",
	"2201": "afroknuc",
	"2202": "amnolys",
	"2203": "beatradi",
	"2204": "blazitup",
	"2205": "dstmusic",
	"2206": "erosion",
	"2207": "fanthree",
	"2208": "hellohap",
	"2209": "lineruin",
	"221": "mirrball",
	"2210": "m1dy_fes",
	"2211": "monopole",
	"2212": "nightsky",
	"2213": "notears",
	"2214": "onmywing",
	"2215": "ravesave",
	"2216": "samsara",
	"2217": "somtimes",
	"2218": "sptoybox",
	"2219": "swtradar",
	"222": "m_prayer",
	"2220": "vulkan",
	"2221": "_x7xl",
	"2222": "zz_amuro",
	"2223": "_izayoi",
	"2224": "_koisiro",
	"2225": "_shiraty",
	"2226": "_verycls",
	"2227": "_dendrob",
	"2228": "_hyouri",
	"2229": "_fakeout",
	"223": "panorama",
	"2230": "_progura",
	"2231": "_basdrop",
	"2232": "_benibtn",
	"2233": "_mottoki",
	"2234": "_therele",
	"2235": "chrono_f",
	"2236": "illumint",
	"2237": "chrono_n",
	"2238": "subtract",
	"2239": "hlywd_ng",
	"224": "putyour",
	"2240": "wesoh_pl",
	"2241": "coloseum",
	"2242": "_trpclub",
	"2243": "litefire",
	"2244": "_jikutrv",
	"2245": "beyond_p",
	"2246": "symmetry",
	"2247": "neogene7",
	"2248": "brokensw",
	"2249": "cinder",
	"225": "sos2nd",
	"2250": "gravigzr",
	"2251": "_lilieze",
	"2252": "faleaves",
	"2253": "entelech",
	"2254": "cosmicat",
	"2255": "rave_it",
	"2256": "ludus_in",
	"2257": "realmaze",
	"2258": "toxicvib",
	"2259": "tiefsee",
	"226": "second",
	"2260": "flashes",
	"2261": "shootfir",
	"2262": "delferia",
	"2263": "chrono_p",
	"2264": "_kyoumei",
	"2265": "sakuramr",
	"2266": "scrfauna",
	"2267": "tadayosi",
	"2268": "_dadada",
	"2269": "_onigami",
	"227": "shake",
	"2270": "_fullpwr",
	"2271": "_toribjt",
	"2272": "scarmoon",
	"2273": "_ayakasi",
	"2274": "_sennen",
	"2275": "_papipu",
	"2276": "ebnyivry",
	"2277": "_shanabi",
	"2278": "say_yeah",
	"2279": "reflux",
	"228": "shineon",
	"2280": "inbreeze",
	"2281": "sosummer",
	"2282": "chronos",
	"2283": "discloze",
	"2284": "invi_mrc",
	"2285": "_dsummer",
	"2286": "_soratad",
	"2287": "_ntdiary",
	"2288": "pendualt",
	"229": "soflan",
	"23": "gambolhs",
	"230": "sptrip",
	"2301": "routing",
	"2302": "_syaku_2",
	"2303": "acidpump",
	"2304": "aublia",
	"2305": "damageps",
	"2306": "dvlsgear",
	"2307": "diacross",
	"2308": "do_thing",
	"2309": "donkdonk",
	"231": "_calcuta",
	"2310": "drmtrain",
	"2311": "dynausao",
	"2312": "evlalast",
	"2313": "exchange",
	"2314": "getready",
	"2315": "gofarawy",
	"2316": "inspirit",
	"2317": "m1dydyna",
	"2318": "msloverz",
	"2319": "nanairo",
	"232": "m_prayr3",
	"2320": "nowhere",
	"2321": "refrain",
	"2322": "ridecore",
	"2323": "setufree",
	"2324": "shelter",
	"2325": "starltdh",
	"2326": "survivor",
	"2327": "toprdise",
	"2328": "transprt",
	"2329": "uh_oh",
	"2330": "wheeljny",
	"2331": "_asayake",
	"2332": "_altbeta",
	"2333": "_syupatu",
	"2334": "_alicein",
	"2335": "_seroton",
	"2336": "_taiysun",
	"2337": "_sunpark",
	"2338": "_stardst",
	"2339": "_meisai",
	"2340": "nightbfr",
	"2341": "_maudand",
	"2342": "cstation",
	"2343": "rock_it",
	"2344": "violrose",
	"2345": "blspring",
	"2346": "derelict",
	"2347": "arcana",
	"2348": "onthefm",
	"2349": "chaoseat",
	"2350": "konzertv",
	"2351": "_sjigoku",
	"2352": "_urara",
	"2353": "godspeed",
	"2354": "viopulse",
	"2355": "glinerds",
	"2356": "ninja_dd",
	"2357": "strlight",
	"2358": "la_dolce",
	"2359": "journeko",
	"2360": "superdup",
	"2361": "sei_teri",
	"2362": "code_1",
	"2363": "ao_1",
	"2364": "generate",
	"2365": "nolimit",
	"2366": "hicharge",
	"2367": "_meikyou",
	"2368": "_azisai",
	"2369": "outbreak",
	"2370": "_gyogyo",
	"2371": "m4k3_1t",
	"2372": "posesion",
	"2373": "daylunch",
	"2374": "199024cl",
	"2375": "outeralt",
	"2376": "x_amuro",
	"2377": "strycatz",
	"2378": "sephirot",
	"2379": "gchariot",
	"2380": "angjelly",
	"2381": "zephyran",
	"2382": "tripleco",
	"2383": "_kasimas",
	"2384": "_ekineko",
	"2385": "nzm",
	"2389": "trill_g",
	"2390": "_saisho3",
	"2391": "blackjcl",
	"2392": "sixproof",
	"2393": "toyboxer",
	"2394": "_omylove",
	"2395": "voltissi",
	"2396": "afterimg",
	"2397": "_mid_war",
	"24": "gracyber",
	"2401": "afection",
	"2402": "amazingm",
	"2403": "asiandst",
	"2404": "b_a_star",
	"2405": "believeu",
	"2406": "beyond_7",
	"2407": "breakovr",
	"2408": "disapear",
	"2409": "elbender",
	"2410": "magical",
	"2411": "modulart",
	"2412": "msanswer",
	"2413": "ooo",
	"2414": "otenamih",
	"2415": "ppypbass",
	"2416": "remedy",
	"2417": "rtshogun",
	"2418": "sarutobi",
	"2419": "saybay",
	"2420": "seasidel",
	"2421": "seizeday",
	"2422": "selfishs",
	"2423": "shuriken",
	"2424": "sinobuzf",
	"2425": "summerbx",
	"2426": "superush",
	"2427": "sclapper",
	"2428": "tcommand",
	"2429": "theangel",
	"2430": "togakusi",
	"2431": "umbral",
	"2432": "xinobikl",
	"2433": "_crahara",
	"2434": "_fuyutbk",
	"2435": "_hikage",
	"2436": "_jiyou",
	"2437": "_karasu",
	"2438": "_magicvl",
	"2439": "_oinochi",
	"2440": "_snbrnka",
	"2441": "_sskasum",
	"2442": "_viva_",
	"2443": "brkchain",
	"2444": "hadesmnk",
	"2445": "_srcof_c",
	"2446": "_kyubi",
	"2447": "_enkyoku",
	"2448": "a_glxy24",
	"2449": "rvcannon",
	"2450": "ylsketch",
	"2451": "steledge",
	"2452": "samurais",
	"2453": "babel_gs",
	"2454": "scrmlife",
	"2455": "_tgryuki",
	"2456": "yamabiko",
	"2457": "_izanami",
	"2458": "skyhigh",
	"2459": "_shime",
	"2460": "goahead",
	"2461": "echidna",
	"2462": "crew",
	"2463": "nostos",
	"2464": "beatjugg",
	"2465": "pianosam",
	"2466": "happyrsh",
	"2467": "_dw_oiwa",
	"2468": "honeytrp",
	"2469": "_tkiyuki",
	"2470": "gungnir",
	"2471": "dornwald",
	"2472": "brogamer",
	"2473": "risehawk",
	"2474": "ao_inf",
	"2475": "fuznrizn",
	"2476": "caterpil",
	"2477": "rain",
	"2478": "egretwil",
	"2479": "macuil",
	"2480": "summerlt",
	"2481": "warrior",
	"2482": "quakes",
	"2483": "marenect",
	"2484": "surfon",
	"2485": "invstrix",
	"2486": "venom",
	"2487": "cyberclr",
	"2488": "_koihado",
	"2489": "vmilion",
	"2490": "lostwing",
	"2491": "_dowakai",
	"2492": "apocalrf",
	"2493": "snkungfu",
	"2494": "_buzra",
	"25": "intworld",
	"2501": "aa_rebld",
	"2502": "abraxas",
	"2503": "accelert",
	"2504": "acdva303",
	"2505": "alphratz",
	"2506": "amrverao",
	"2507": "arca",
	"2508": "backspin",
	"2509": "btground",
	"2510": "bestofme",
	"2511": "brstatis",
	"2512": "chaserxx",
	"2513": "chemicoo",
	"2514": "cosmicwd",
	"2515": "deadheat",
	"2516": "exh_hype",
	"2517": "freedom",
	"2518": "futuredd",
	"2519": "get_up",
	"2520": "hattrick",
	"2521": "helladep",
	"2522": "iloveyou",
	"2523": "imcoming",
	"2524": "luvdrive",
	"2525": "mid_lady",
	"2526": "mira",
	"2527": "no2dance",
	"2528": "nbtheory",
	"2529": "o_d_20",
	"2530": "only4now",
	"2531": "speed",
	"2532": "spedemon",
	"2533": "staticst",
	"2534": "t_anubis",
	"2535": "tcannonb",
	"2536": "thechase",
	"2537": "ummu",
	"2538": "vox_rush",
	"2539": "xperanza",
	"2540": "1001escp",
	"2541": "_ediblef",
	"2542": "_hibiscs",
	"2543": "_jdesire",
	"2544": "_kyouhan",
	"2545": "_lastcen",
	"2546": "_nitcity",
	"2547": "_psougen",
	"2548": "_usakame",
	"2549": "b_a_hero",
	"2550": "_resonan",
	"2551": "songabba",
	"2552": "beastmod",
	"2553": "fireball",
	"2554": "expanded",
	"2555": "dthzigoq",
	"2556": "prsphone",
	"2557": "papilio",
	"2558": "_bathrom",
	"2559": "_inochi",
	"2560": "encountr",
	"2561": "booboost",
	"2562": "_tksinwa",
	"2563": "nitrous",
	"2564": "_paradox",
	"2565": "a_future",
	"2566": "rrailgun",
	"2567": "citynvrs",
	"2568": "rampage",
	"2569": "rcircuit",
	"2570": "npapabbq",
	"2571": "_simurgh",
	"2572": "trevovip",
	"2573": "hypecr25",
	"2574": "illuswtr",
	"2575": "emeralds",
	"2576": "revolver",
	"2577": "dropz_ln",
	"2578": "2player",
	"2579": "lits_evo",
	"2580": "sunlight",
	"2581": "slipstrm",
	"2582": "anagma",
	"2583": "starjunc",
	"2584": "fervidex",
	"2585": "_babibu",
	"2586": "lifegame",
	"2587": "einehaub",
	"2588": "initiatn",
	"2589": "255_255",
	"2590": "antigrav",
	"2591": "maxivcrd",
	"2592": "sleeples",
	"2593": "ltbounce",
	"2594": "anchor",
	"26": "jamregae",
	"2601": "again",
	"2602": "angeldmn",
	"2603": "comaaaaa",
	"2604": "cranbery",
	"2605": "dauntl3s",
	"2606": "dskipper",
	"2607": "dr_chemi",
	"2608": "emberlts",
	"2609": "glory",
	"2610": "heisei",
	"2611": "hotlimit",
	"2612": "huryhury",
	"2613": "idc",
	"2614": "idolsynd",
	"2615": "ltmecure",
	"2616": "lfo",
	"2617": "levelone",
	"2618": "overtime",
	"2619": "ptclarts",
	"2620": "psysheep",
	"2621": "rockonna",
	"2622": "rootage",
	"2623": "serious",
	"2624": "sprocker",
	"2625": "starrynt",
	"2626": "t_bestof",
	"2627": "t_jubila",
	"2628": "t_rebeli",
	"2629": "twi_warp",
	"2630": "usa",
	"2631": "urbancon",
	"2632": "wing_hts",
	"2633": "won_chu",
	"2634": "wndrland",
	"2635": "xlo",
	"2636": "yumjelly",
	"2637": "_hanakan",
	"2638": "_sappare",
	"2639": "_scndear",
	"2640": "_ntnnioi",
	"2641": "_hbfesta",
	"2642": "_bouqann",
	"2643": "_mausole",
	"2644": "atalehdn",
	"2645": "gigathra",
	"2646": "_granada",
	"2647": "xenon2",
	"2648": "catchfir",
	"2649": "killeach",
	"2650": "sigma",
	"2651": "_bakzeni",
	"2652": "losttech",
	"2653": "rozaanda",
	"2654": "drasticd",
	"2655": "_k_hiori",
	"2656": "ladybird",
	"2657": "wolf1061",
	"2658": "undrholo",
	"2659": "playfire",
	"2660": "painfate",
	"2661": "red_jack",
	"2662": "carryme",
	"2663": "re_story",
	"2664": "_kai_den",
	"2665": "_dakismt",
	"2666": "blossom",
	"2667": "unbelief",
	"2668": "evanscnt",
	"2669": "necroxis",
	"2670": "machomnk",
	"2671": "50th_bgn",
	"2672": "carmina",
	"2673": "_and_int",
	"2674": "50th_ftr",
	"2675": "50th_flg",
	"2676": "50th_bmn",
	"2677": "lifthigh",
	"2678": "_shinair",
	"2679": "nexttale",
	"2680": "garuda",
	"2681": "zendegi",
	"2682": "hrdbrain",
	"2683": "onigoros",
	"2684": "techcolr",
	"2685": "code_0",
	"2686": "geirskog",
	"2687": "ruinopal",
	"2688": "visterhv",
	"2689": "coscyber",
	"2690": "gene",
	"2691": "nightx3",
	"2692": "t_sealer",
	"2693": "pls_mr_c",
	"2694": "_candykd",
	"2695": "_taito26",
	"2696": "go_glare",
	"2697": "lethalwp",
	"27": "lvgroovy",
	"2701": "beataffe",
	"2702": "bharmony",
	"2703": "calvados",
	"2704": "changeys",
	"2705": "dowhat",
	"2706": "dropit",
	"2707": "duration",
	"2708": "excite",
	"2709": "fairycok",
	"2710": "holdhand",
	"2711": "hypdrive",
	"2712": "infmiror",
	"2713": "mel",
	"2714": "movingon",
	"2715": "nastytec",
	"2716": "newalone",
	"2717": "nrgstr86",
	"2718": "ohayo",
	"2719": "oplanets",
	"2720": "popteamk",
	"2721": "prmvibes",
	"2722": "q_kaguya",
	"2723": "rainstrm",
	"2724": "ravelith",
	"2725": "silylove",
	"2726": "skashall",
	"2727": "t_rex_vs",
	"2728": "tecstyle",
	"2729": "thebrave",
	"2730": "triumph",
	"2731": "unitehrt",
	"2732": "valkyris",
	"2733": "virusfnk",
	"2734": "vldragon",
	"2735": "_gabriel",
	"2736": "_mandara",
	"2737": "_oratoky",
	"2738": "_reiwa_r",
	"2739": "_shinen",
	"2740": "_sepiano",
	"2741": "_valse27",
	"2742": "_rankerk",
	"2743": "voodooba",
	"2744": "27thstyl",
	"2745": "thefaust",
	"2746": "like_it",
	"2747": "ravepatr",
	"2748": "screwowo",
	"2749": "lightstr",
	"2750": "phasesft",
	"2751": "crankit",
	"2752": "and_roid",
	"2753": "sugardrp",
	"2754": "override",
	"2755": "backyard",
	"2756": "gigaviol",
	"2757": "theory",
	"2758": "akashicb",
	"2759": "_rensein",
	"2760": "bowshock",
	"2761": "mattsilv",
	"2762": "hpromise",
	"2763": "shiva",
	"2764": "lords_rt",
	"2765": "inffomal",
	"2766": "flyabv_p",
	"2767": "lcrust_h",
	"2768": "_gatturi",
	"2769": "_hiraki",
	"2770": "vibra",
	"2771": "stoichyp",
	"2772": "sellout",
	"2773": "punchdwn",
	"2774": "lostsoul",
	"2775": "ddribble",
	"2776": "level2",
	"2777": "tsadness",
	"2778": "btprison",
	"2779": "takemekh",
	"2780": "_stellad",
	"2781": "vinculum",
	"2782": "_lvkiras",
	"2783": "evermesg",
	"2784": "_shaku_r",
	"2785": "sick_r",
	"2786": "_psaso_r",
	"2787": "roughper",
	"2788": "friction",
	"2789": "ifpaslam",
	"2790": "artist",
	"2791": "s_smilin",
	"2792": "into_mad",
	"2793": "_enyummy",
	"2794": "forgetmc",
	"2795": "orca",
	"2796": "_badends",
	"2797": "_shamshr",
	"2798": "megalara",
	"2799": "ypsilon",
	"28": "luvdis3a",
	"2801": "dstmsc_k",
	"2802": "eulagoon",
	"2803": "gigaraid",
	"2804": "herweare",
	"2805": "highvolt",
	"2806": "iiredryu",
	"2807": "lastday",
	"2808": "lhcowboy",
	"2809": "middrive",
	"2810": "of_magni",
	"2811": "psiempre",
	"2812": "plkmania",
	"2813": "rubaduba",
	"2814": "vitrum",
	"2815": "whenimet",
	"2816": "_dogumbr",
	"2817": "_namidam",
	"2818": "_mkakure",
	"2819": "_suikyo",
	"2820": "_minatki",
	"2821": "_turn_a",
	"2822": "ahahyeah",
	"2823": "big_smtm",
	"2824": "brkrules",
	"2825": "fw_marra",
	"2826": "ovrslept",
	"2827": "chewingd",
	"2828": "_gurenge",
	"2829": "tmrwknsb",
	"2830": "_stakara",
	"2831": "romatoma",
	"2832": "bpltheme",
	"2833": "amrita",
	"2834": "emprfury",
	"2835": "mrsbeach",
	"2836": "ocanblue",
	"2837": "ptystart",
	"2838": "rommmo",
	"2839": "rowdy",
	"2840": "s_bahn",
	"2841": "sopunky",
	"2842": "swarmofs",
	"2843": "wakeupnw",
	"2844": "_mugen_m",
	"2845": "firebeat",
	"2846": "x_binary",
	"2847": "tpeerles",
	"2848": "connect_",
	"2849": "handsupr",
	"2850": "twindchn",
	"2851": "3idolonf",
	"2852": "_sekaiop",
	"2853": "_ope_143",
	"2854": "crazy_jp",
	"2855": "explorer",
	"2856": "viridian",
	"2857": "_feastof",
	"2858": "_grk",
	"2859": "asian_vr",
	"2860": "sss_rrr",
	"2861": "rubpiano",
	"2862": "brnflame",
	"2863": "thatfeel",
	"2864": "megaera",
	"2865": "abso_k",
	"2866": "souhaitb",
	"2867": "dawnsaga",
	"2868": "_65c",
	"2869": "neoherit",
	"2870": "ritual_a",
	"2871": "scandal",
	"2872": "sugarplm",
	"2873": "_badswts",
	"2874": "_hakakoi",
	"2875": "inorevol",
	"2876": "apolioth",
	"2877": "blkwhite",
	"2878": "_dscrdia",
	"2879": "tiempolc",
	"2880": "tellwhat",
	"2881": "asyuwant",
	"2882": "brahma",
	"2883": "parvati",
	"2884": "rosaazul",
	"2885": "_vajra",
	"2886": "_a_rvnant",
	"2887": "jungleat",
	"2888": "winproof",
	"2889": "_unphilo",
	"2890": "otokozak",
	"2891": "ignisira",
	"2892": "sinusiri",
	"2893": "frisksqk",
	"2894": "zenith",
	"2895": "danzaest",
	"2896": "cosmcray",
	"2897": "level3",
	"2898": "locustrv",
	"29": "luvdisco",
	"2901": "angeladd",
	"2902": "ariah",
	"2903": "bluebird",
	"2904": "disparat",
	"2905": "donthype",
	"2906": "dreamufo",
	"2907": "fantamgr",
	"2908": "fegrix",
	"2909": "fnlblaze",
	"2910": "gigagahl",
	"2911": "heartach",
	"2912": "ilayza",
	"2913": "lparotia",
	"2914": "livedriv",
	"2915": "n_o_",
	"2916": "nodaybut",
	"2917": "nstprock",
	"2918": "onyx",
	"2919": "power_",
	"2920": "piratesb",
	"2921": "proprops",
	"2922": "pperplex",
	"2923": "skrmsalv",
	"2924": "slwyvern",
	"2925": "tailight",
	"2926": "tricross",
	"2927": "ventrilq",
	"2928": "vcravers",
	"2929": "votaniab",
	"2930": "wdescape",
	"2931": "xyndrome",
	"2932": "808monky",
	"2933": "_damonis",
	"2934": "_hitokio",
	"2935": "_itoshik",
	"2936": "_kuchikr",
	"2937": "_oddloop",
	"2938": "_odo",
	"2939": "_oortcld",
	"2940": "_silvous",
	"2941": "_utusimi",
	"2942": "_tktmilk",
	"2943": "_gmaster",
	"2944": "gamechng",
	"2945": "hatsurpr",
	"2946": "tomahawk",
	"2947": "oneforal",
	"2948": "bravespr",
	"2949": "emotripr",
	"2950": "ergosphr",
	"2951": "sparknit",
	"2952": "_nightfc",
	"2953": "korskhow",
	"2954": "_misogi",
	"2955": "altnator",
	"2956": "aftrmath",
	"2957": "_kaibutu",
	"2958": "_mschour",
	"2959": "_gudafwa",
	"2960": "_medetee",
	"2961": "stepper",
	"2962": "_bgrotto",
	"2963": "bangerx4",
	"2964": "slbullet",
	"2965": "binarybh",
	"2969": "absoevil",
	"2970": "n_a",
	"2971": "anemone",
	"2972": "_krobeni",
	"2973": "noct2097",
	"2974": "legendtr",
	"2975": "_hrenten",
	"2976": "plasmasn",
	"2977": "pushonbt",
	"2978": "smalt",
	"2979": "rage_h14",
	"2980": "_akumafk",
	"2981": "emera",
	"2982": "pout",
	"2983": "_amanojk",
	"2984": "flcastle",
	"2985": "wha",
	"2986": "_pkaijin",
	"2987": "divinehv",
	"2988": "vr_kmnz",
	"2989": "_aitsura",
	"2990": "_goodbys",
	"2991": "amicable",
	"2992": "getsetgo",
	"2993": "10000mil",
	"2994": "arkadia",
	"2995": "hd_wired",
	"2996": "seeyouag",
	"2997": "cultinvi",
	"2998": "resonant",
	"2999": "akatsuki",
	"3": "511_hs",
	"30": "meltarms",
	"3000": "sowhat",
	"3001": "3v0",
	"3002": "anthracn",
	"3003": "b_o_d_y_",
	"3004": "badencry",
	"3005": "cccnnn",
	"3006": "cuerscue",
	"3007": "driver",
	"3008": "ezdodanc",
	"3009": "getupagn",
	"301": "almostlv",
	"3010": "lads",
	"3011": "lunaplna",
	"3012": "meissa",
	"3013": "moveurbd",
	"3014": "noborder",
	"3015": "pengging",
	"3016": "perfplan",
	"3017": "progenom",
	"3018": "rewindtm",
	"3019": "rulerorl",
	"302": "artific",
	"3020": "seraph",
	"3021": "shadowld",
	"3022": "summerbl",
	"3023": "sundayvb",
	"3024": "tcphobia",
	"3025": "timemchn",
	"3026": "volca_bb",
	"3027": "wanna_bg",
	"3028": "withyu30",
	"3029": "_3plus3",
	"303": "btmachn",
	"3030": "_itsuoto",
	"3031": "_otose_t",
	"3032": "_kyundes",
	"3033": "_hgensou",
	"3034": "_tkiyume",
	"3035": "_slonely",
	"3036": "_ikiruyo",
	"3037": "_mybabel",
	"3038": "_cathsin",
	"3039": "_amepano",
	"304": "cantstop",
	"3040": "_kyouka",
	"3041": "rinne",
	"3042": "i_chroma",
	"3043": "_rinne_k",
	"3044": "_dentity",
	"3045": "volaquas",
	"3046": "_orderbr",
	"3047": "get_feet",
	"3048": "overvolt",
	"3049": "hatsurp2",
	"305": "coldpls",
	"3050": "_oulgnds",
	"3051": "nextlevl",
	"3052": "redsoul",
	"3053": "starbeat",
	"3054": "fadstars",
	"3055": "diajackl",
	"3056": "_aru_b",
	"3057": "peaktime",
	"3058": "louderrt",
	"3059": "_k_verga",
	"306": "dontstop",
	"3060": "_expulsn",
	"3061": "_choe",
	"3062": "one_only",
	"3063": "superfrk",
	"3064": "level4",
	"3065": "zenithsv",
	"3066": "tclown24",
	"3067": "_r_s_x_n",
	"3068": "_s_jidai",
	"3069": "_kamipoi",
	"307": "dream",
	"3070": "king",
	"3071": "_matuken",
	"3072": "korsklng",
	"3073": "beyondev",
	"3074": "_shvnccd",
	"3075": "dicadica",
	"3076": "awaawa",
	"3077": "exodusgn",
	"3078": "straitst",
	"3079": "glacia",
	"308": "dynamite",
	"3080": "chaotoxn",
	"3081": "_eikan_c",
	"3082": "bigwaver",
	"3083": "somnidis",
	"3084": "_ksmoyou",
	"3085": "7colors",
	"3086": "ambush_a",
	"3087": "_kmscena",
	"3088": "_zoshoku",
	"3089": "xerulean",
	"309": "endofcen",
	"3090": "flare",
	"3091": "_pfeater",
	"3092": "caldwl99",
	"3093": "_ccj_oni",
	"3094": "ccrimson",
	"3095": "max_360",
	"3096": "suspcion",
	"3097": "_isnpyon",
	"3098": "_heisoku",
	"3099": "_zanzoni",
	"31": "melt_cs",
	"310": "eranos",
	"3101": "20xx",
	"3102": "aeterna",
	"3103": "bitlucky",
	"3104": "chemiclr",
	"3105": "dahlia",
	"3106": "dazzleat",
	"3107": "deepseam",
	"3108": "esunfall",
	"3109": "frequent",
	"311": "fathoms",
	"3110": "game_on",
	"3111": "gethighr",
	"3112": "ghostpls",
	"3113": "gloriosa",
	"3114": "iris",
	"3115": "jumper",
	"3116": "justiceg",
	"3117": "mukade",
	"3118": "myswbird",
	"3119": "shapesft",
	"312": "garden",
	"3120": "solarecl",
	"3121": "speculat",
	"3122": "submerge",
	"3123": "tclubmzk",
	"3124": "timedist",
	"3125": "ttnrider",
	"3126": "tripjump",
	"3127": "_idol",
	"3128": "_atashi",
	"3129": "_kizutkd",
	"313": "getsight",
	"3130": "_cindrla",
	"3131": "_cntismr",
	"3132": "_chutayo",
	"3133": "_neokiys",
	"3134": "_hatasen",
	"3135": "_nairtin",
	"3136": "_natkaze",
	"3137": "_matenro",
	"3138": "_ymenisi",
	"3139": "_ruoumon",
	"314": "holic",
	"3140": "_retrver",
	"3141": "_plrayer",
	"3142": "hardbrkr",
	"3143": "_denkou",
	"3144": "hatsurp3",
	"3145": "i_ii",
	"3146": "getwickd",
	"3147": "redeterm",
	"3148": "sirius",
	"3149": "_shuen_c",
	"315": "isthis",
	"3150": "_shaku_c",
	"3151": "_k_gomen",
	"3152": "_phony",
	"3153": "_devilja",
	"3154": "psychint",
	"3155": "zeroinon",
	"3156": "inherita",
	"3157": "winkle2w",
	"3158": "outcntrl",
	"3159": "vercarol",
	"316": "lot",
	"3160": "_polauta",
	"3161": "_meumeuz",
	"3162": "_densini",
	"3163": "out_disk",
	"3164": "glhammer",
	"3165": "maxcheat",
	"3166": "glitch_n",
	"3167": "monkeybs",
	"3168": "xb10r",
	"3169": "ambiverm",
	"317": "leading",
	"3170": "cntsheep",
	"3171": "justgime",
	"3172": "swordven",
	"3173": "mldollar",
	"3174": "cadenza",
	"3175": "stereobt",
	"3176": "demonmch",
	"3177": "_waktetu",
	"3178": "_shou",
	"3179": "_yoidore",
	"318": "letstalk",
	"3180": "_yuusha",
	"3181": "_marsmax",
	"3182": "_kamitre",
	"3183": "amethyst",
	"3184": "tripdeep",
	"3185": "act0",
	"3186": "_dennots",
	"3187": "tlastapo",
	"3188": "level5",
	"3189": "pilgrim",
	"319": "makemove",
	"3190": "_koyoiry",
	"3191": "ndlsmlfy",
	"3192": "code_2",
	"3193": "vulnerab",
	"3194": "seventm4",
	"3195": "troll",
	"3196": "riffrain",
	"3197": "_rabbith",
	"3198": "_aipaidh",
	"3199": "theonly1",
	"32": "ovdoser",
	"320": "nvrdown",
	"3201": "adamant",
	"3202": "blingbbb",
	"3203": "brngfire",
	"3204": "chaosunb",
	"3205": "chsafter",
	"3206": "dstntion",
	"3207": "digiradi",
	"3208": "dreamshp",
	"3209": "dropsynd",
	"321": "presto",
	"3210": "eleanor",
	"3211": "elysium",
	"3212": "fermipdx",
	"3213": "fierystl",
	"3214": "gtstmind",
	"3215": "here_now",
	"3216": "kotonoha",
	"3217": "lowercas",
	"3218": "mvp",
	"3219": "noixia",
	"322": "r5",
	"3220": "perhuman",
	"3221": "pitapat",
	"3222": "pop_eden",
	"3223": "rspotion",
	"3224": "ravesynd",
	"3225": "satburst",
	"3226": "secrouge",
	"3227": "spaceint",
	"3228": "ugottabt",
	"3229": "vibingsk",
	"323": "reincar",
	"3230": "_amedama",
	"3231": "_igaku",
	"3232": "_edamame",
	"3233": "_oddlove",
	"3234": "_saikyog",
	"3235": "_shakuls",
	"3236": "_sparkht",
	"3237": "_gestalt",
	"3238": "_danzai1",
	"3239": "_bibbidi",
	"324": "rightnow",
	"3240": "_mesmerz",
	"3241": "_fletter",
	"3242": "lightspd",
	"3243": "cosmcv3l",
	"3244": "_musou",
	"3245": "exmasive",
	"3246": "arcanos",
	"3247": "bang_boo",
	"3248": "divjudge",
	"3249": "_hazerya",
	"325": "sos3rd",
	"3250": "_shokyok",
	"3251": "roarchro",
	"3252": "_we_idol",
	"3253": "_donut24",
	"3254": "_dremchu",
	"3255": "slumberp",
	"3256": "showlove",
	"3257": "mid_crnr",
	"3258": "_cantata",
	"3259": "_obsomet",
	"326": "schlag",
	"3260": "_hao",
	"3261": "_romaesc",
	"3262": "constell",
	"3263": "flyawayb",
	"3264": "horadeve",
	"3265": "_haruiro",
	"3266": "_kiminos",
	"3267": "withouth",
	"3268": "godmind",
	"3269": "sugarush",
	"327": "sense3a",
	"3270": "_dmsinko",
	"3271": "sheroine",
	"3272": "_kyukura",
	"3273": "_sindame",
	"3274": "marlin",
	"3275": "mightyct",
	"3276": "_pastlsm",
	"3277": "stgztrip",
	"3278": "_sukitte",
	"3279": "aqvion",
	"328": "sense",
	"3280": "skedulv1",
	"3281": "_explore",
	"3282": "_kakugos",
	"3283": "_gyalaxy",
	"3284": "plazma",
	"3285": "_kissktn",
	"3286": "galaxyco",
	"3287": "goodlook",
	"3288": "evereuph",
	"3289": "_arabhyp",
	"329": "skin",
	"3290": "uaigh",
	"3291": "buttwist",
	"3292": "xhronoxp",
	"3293": "inbetwen",
	"3294": "sisyphus",
	"3295": "eyeheavn",
	"3296": "shirdal",
	"3297": "tcrumble",
	"3298": "flamingo",
	"3299": "pinkycrz",
	"33": "patsen",
	"330": "scraper",
	"3301": "a_certif",
	"3302": "agetekeo",
	"3303": "bangdanc",
	"3304": "carapain",
	"3305": "c_gatcha",
	"3306": "countdhh",
	"3307": "discokil",
	"3308": "fashionf",
	"3309": "frmhuman",
	"331": "takeonme",
	"3310": "justsync",
	"3311": "lemonmel",
	"3312": "makin_it",
	"3313": "memoriao",
	"3314": "mochidrm",
	"3315": "nyanuniv",
	"3316": "pallete",
	"3317": "rally_25",
	"3318": "regina_v",
	"3319": "shiningd",
	"332": "tangern",
	"3320": "snapskip",
	"3321": "spc_s4to",
	"3322": "splash_",
	"3323": "substanc",
	"3324": "vitamin",
	"3325": "2beconti",
	"3326": "_ignirru",
	"3327": "_kawaiid",
	"3328": "_kyozots",
	"3329": "_gryoran",
	"333": "tange_hs",
	"3330": "_sraikan",
	"3331": "_sorebok",
	"3332": "_delamuu",
	"3333": "_dpdrill",
	"3334": "_natsere",
	"3335": "_bubblin",
	"3336": "_vividkr",
	"3337": "_hyakkoi",
	"3338": "_bl_clvr",
	"3339": "_monmeta",
	"334": "t_safari",
	"3340": "_rconfit",
	"34": "perfect",
	"35": "prince",
	"36": "qjamaica",
	"37": "r3",
	"38": "salaman",
	"39": "skaagogo",
	"3902": "321stars",
	"3903": "5eternal",
	"3904": "80s_caps",
	"3905": "acidvis",
	"3906": "a_galaxy",
	"3908": "atkmusic",
	"3909": "backfwfv",
	"3910": "btltrain",
	"3911": "begin_cr",
	"3913": "beyond",
	"3914": "biometri",
	"3915": "bleedluv",
	"3916": "b_mirage",
	"3917": "brainstm",
	"3918": "breathls",
	"3919": "cracker",
	"3921": "caldera",
	"3922": "clbrtion",
	"3923": "chain_of",
	"3924": "change_r",
	"3925": "claiomh",
	"3926": "cookie_b",
	"3927": "crymson",
	"3929": "dengue",
	"3930": "denim",
	"3933": "drkmonky",
	"3934": "dune",
	"3935": "elecfied",
	"3936": "elecgasm",
	"3937": "endless",
	"3938": "eraserdd",
	"3939": "eraser",
	"3941": "feelinlv",
	"3943": "firstday",
	"3944": "flag_pce",
	"3945": "fromtime",
	"3946": "funktown",
	"3947": "go_brzk",
	"3948": "gobble",
	"3949": "guilt_lv",
	"3950": "guilty",
	"3952": "gymno009",
	"3953": "helsca_t",
	"3954": "hybrid_l",
	"3955": "hypecore",
	"3956": "icecube",
	"3957": "implant",
	"3960": "inf_ffs",
	"3961": "ixion",
	"3962": "jelly_r",
	"3963": "liftmeup",
	"3964": "ltmotion",
	"3966": "lovebox",
	"3968": "mnemoniq",
	"3969": "prmnesia",
	"3971": "playball",
	"3972": "pluto",
	"3973": "pratfall",
	"3975": "q_master",
	"3977": "recollec",
	"3978": "ref_eden",
	"3979": "replay",
	"3980": "rizingup",
	"3981": "sana_blt",
	"3982": "saturn",
	"3983": "sequence",
	"3984": "shoot_em",
	"3986": "shox",
	"3987": "sidchain",
	"3988": "stepinto",
	"3989": "strwoman",
	"3990": "suggest",
	"3991": "sunshero",
	"3992": "shighway",
	"3994": "symptom",
	"3995": "the_deto",
	"3996": "t_100sec",
	"3998": "theway_u",
	"3999": "time2emp",
	"4": "22dunk",
	"40": "spenergy",
	"4000": "torino_k",
	"4001": "toxic",
	"4002": "toycube",
	"4003": "tmission",
	"4004": "treastar",
	"4005": "troposph",
	"4006": "turning",
	"4008": "unicorn",
	"4009": "usualday",
	"401": "250bpm",
	"4010": "vanishpt",
	"4011": "vinsanty",
	"4012": "vox_up",
	"4013": "water_cb",
	"4014": "welcome",
	"4016": "whatnext",
	"4017": "yougotme",
	"4018": "_evryday",
	"4019": "_tamayra",
	"402": "absolute",
	"4021": "_taito",
	"4022": "_kazedrm",
	"4023": "_j_final",
	"4024": "firstemo",
	"4025": "voxup_sp",
	"4026": "_jfinala",
	"4027": "gobblecp",
	"4028": "3y3s_l",
	"4029": "rejegirl",
	"403": "b4u",
	"4030": "clione_r",
	"4031": "graviton",
	"4032": "_akatoao",
	"4033": "_setsujo",
	"4034": "remain",
	"4035": "_shizuku",
	"4036": "harmonia",
	"4037": "spacedog",
	"4038": "amabie",
	"4039": "tsarbomb",
	"404": "broken",
	"4040": "_romirob",
	"4041": "concon",
	"4042": "squall",
	"4043": "gimmeabb",
	"4044": "1116dust",
	"4045": "_sripple",
	"4046": "toolates",
	"4047": "24h_race",
	"4048": "haleluja",
	"4049": "chocopla",
	"405": "burnflr",
	"4050": "trickytr",
	"4051": "doitama",
	"4052": "stleq",
	"4053": "bl_lazer",
	"4054": "vector",
	"4055": "lycoris",
	"4056": "all_ok",
	"4057": "_ruijo_k",
	"4058": "limtoppa",
	"4059": "mana",
	"406": "checking",
	"4060": "uen",
	"4061": "_love2sg",
	"4062": "_rememx2",
	"4063": "_jtandem",
	"4064": "_mikanse",
	"4065": "feedingf",
	"4066": "ppphase",
	"4067": "cosycata",
	"4068": "crosfire",
	"4069": "cybercon",
	"407": "clione",
	"4070": "dynasty",
	"4071": "fakestl2",
	"4072": "ignitedn",
	"4073": "proguniv",
	"4074": "_caralno",
	"4075": "_geo_tea",
	"4076": "notehway",
	"4077": "groove04",
	"4078": "hlyeappy",
	"4079": "jetworld",
	"408": "conga",
	"4080": "sprbeast",
	"4081": "100seckb",
	"4082": "_exister",
	"4083": "_kiyaror",
	"4084": "_k_iroha",
	"4085": "airflowr",
	"4086": "coldmoon",
	"4087": "insprtgg",
	"4088": "popnsoda",
	"4089": "ghelnaga",
	"409": "diamond",
	"41": "spen_dd",
	"410": "dxy",
	"411": "empathy",
	"412": "erastep",
	"413": "fantasy",
	"414": "fcd",
	"415": "flowers",
	"416": "getwild",
	"417": "girigiri",
	"418": "higher",
	"419": "hitch2",
	"42": "therhyme",
	"420": "im4real",
	"421": "infinite",
	"422": "jamarma",
	"423": "jive",
	"424": "kamikaze",
	"425": "lovewill",
	"426": "luvuchi",
	"427": "mnmlian",
	"428": "mr_t",
	"429": "nasty",
	"43": "tflojack",
	"430": "nycity",
	"431": "north",
	"432": "nothing",
	"433": "restmind",
	"434": "r10k",
	"435": "sanamol",
	"436": "sanctus",
	"437": "smallwav",
	"438": "starmine",
	"439": "sweetlab",
	"44": "yumakeme",
	"440": "twinbee",
	"441": "ultrahh",
	"442": "undercon",
	"443": "vienna",
	"444": "voltage",
	"446": "swtlab24",
	"448": "hitch228",
	"45": "perfect1",
	"47": "celeb4",
	"48": "patsen4",
	"5": "beinpara",
	"501": "1989",
	"502": "abyss",
	"503": "comewith",
	"504": "deadline",
	"505": "estella",
	"506": "flashof",
	"507": "givesign",
	"508": "iidx",
	"509": "inmyeyes",
	"51": "astrogzr",
	"510": "insert",
	"511": "kissme",
	"512": "loveage",
	"513": "mobomoga",
	"514": "outwall",
	"515": "ovcloud",
	"516": "qqq",
	"517": "radical",
	"518": "real",
	"519": "regulus",
	"52": "insdinst",
	"520": "remem_u",
	"521": "rideon",
	"522": "rislim",
	"523": "sometime",
	"524": "spin",
	"525": "stheart",
	"526": "stwords",
	"527": "sync",
	"528": "tablets",
	"529": "tvoyager",
	"53": "onslaugh",
	"530": "thecube",
	"531": "tpolaris",
	"532": "tpola_us",
	"533": "tpola_c4",
	"534": "tpola_17",
	"535": "timoney",
	"536": "v_taka",
	"537": "virtual",
	"538": "_tenkiss",
	"54": "reflexes",
	"540": "sometm27",
	"55": "staygold",
	"56": "vvddebut",
	"57": "wildfire",
	"58": "_dkenkai",
	"59": "_tanpopo",
	"6": "bnsolong",
	"60": "metagame",
	"601": "19novem",
	"603": "20novem",
	"604": "amorning",
	"605": "ballad",
	"606": "btydays",
	"607": "bluebry",
	"608": "buffalo",
	"609": "colors",
	"61": "sinkinto",
	"610": "comment",
	"611": "dive",
	"612": "dfatima",
	"613": "fivereg",
	"614": "flowtat",
	"615": "flyaway",
	"616": "ftn",
	"617": "frestyl",
	"618": "frozen",
	"619": "g2",
	"62": "tsetsunb",
	"620": "justdoit",
	"621": "lamour",
	"622": "linus",
	"623": "lvdream",
	"624": "m02stp",
	"625": "nemesis",
	"626": "nightof",
	"627": "ppprdise",
	"628": "reallove",
	"629": "romeo",
	"63": "_kofusei",
	"630": "rotsun",
	"631": "r80s_emp",
	"633": "silhoet",
	"634": "somewon",
	"635": "summer",
	"636": "take_ez",
	"637": "vjarmy",
	"638": "wow70",
	"639": "y31",
	"64": "_dusanko",
	"640": "yester",
	"641": "_kotti",
	"642": "_theme_j",
	"643": "somewonc",
	"644": "vjarmy26",
	"645": "lamour31",
	"65": "_reimeij",
	"66": "_rbwflvr",
	"7": "begining",
	"701": "2002",
	"702": "9oclocks",
	"703": "a_amuro",
	"704": "ave_rapi",
	"705": "bad_rtn",
	"706": "bringher",
	"707": "bringdjt",
	"708": "burnheat",
	"709": "burnup",
	"710": "cheertra",
	"711": "cloudy",
	"712": "d2r",
	"713": "destiny",
	"714": "evcafe",
	"715": "entrance",
	"716": "foreplay",
	"717": "generald",
	"718": "general",
	"719": "glorious",
	"720": "gravity",
	"721": "happywed",
	"722": "heartbt",
	"723": "i_feel",
	"724": "lastmsg",
	"725": "letsnow",
	"726": "lovegene",
	"727": "lovemedo",
	"728": "marm_rev",
	"729": "max300",
	"730": "moredeep",
	"731": "nvrlook",
	"732": "newyork",
	"733": "remem_m",
	"734": "secret",
	"735": "solid_g",
	"736": "somebody",
	"737": "spica",
	"738": "spooky",
	"739": "stoic",
	"740": "tsilence",
	"741": "tgoodbye",
	"742": "tomorrow",
	"743": "traces",
	"744": "zeroone",
	"745": "_kakumei",
	"746": "smbody29",
	"747": "max_300",
	"801": "abstract",
	"802": "airflow",
	"803": "alienwld",
	"804": "allright",
	"805": "attitude",
	"806": "bitmania",
	"807": "blame",
	"808": "blownmy",
	"809": "celenite",
	"810": "colors_y",
	"811": "dancer",
	"812": "dissolve",
	"813": "disolv16",
	"814": "drivin",
	"815": "dual",
	"816": "fluteman",
	"817": "found",
	"818": "fkbingo",
	"819": "giudecca",
	"820": "halfway",
	"821": "hormiga",
	"822": "hbgate",
	"823": "icf5800",
	"824": "jellyemp",
	"826": "lab",
	"827": "lvorange",
	"828": "luv2feel",
	"829": "memories",
	"830": "monkey",
	"831": "murmur",
	"832": "musicto",
	"833": "outlmtdd",
	"834": "outlmts",
	"835": "outlmt16",
	"836": "please",
	"837": "rbwflyer",
	"838": "rnikita",
	"839": "smlclone",
	"840": "smoke",
	"841": "stmach3",
	"842": "stardrm",
	"843": "stick",
	"844": "symbolic",
	"845": "thunder",
	"846": "tribal",
	"847": "v35",
	"848": "wargame",
	"849": "wwlove",
	"850": "xenon",
	"851": "_tstrong",
	"852": "_sakura",
	"853": "_aoisho",
	"854": "_yorusun",
	"855": "hbgate25",
	"9": "begin1st",
	"901": "abyss_r",
	"902": "act",
	"903": "advance",
	"904": "atmcage",
	"905": "bbbass",
	"906": "bag",
	"907": "berock_u",
	"908": "breeding",
	"909": "bright",
	"910": "charlot",
	"911": "cradle",
	"912": "distress",
	"913": "dreamin",
	"914": "emo2003",
	"915": "echoes",
	"916": "festa",
	"917": "fun",
	"918": "golden",
	"919": "honey",
	"920": "hyper_eb",
	"921": "icanfly",
	"922": "iwas_r",
	"923": "imin_r",
	"924": "karma",
	"925": "letsnowr",
	"926": "lethello",
	"927": "lightscs",
	"928": "logic",
	"929": "lovedrow",
	"930": "lvshine",
	"931": "loworld",
	"932": "mad_emp",
	"934": "maria",
	"935": "m_child",
	"936": "oneeight",
	"937": "ovcloudr",
	"938": "parasurv",
	"939": "powerdrm",
	"940": "prelude",
	"941": "quasar",
	"942": "quicken",
	"943": "really",
	"944": "rislimr",
	"945": "rot_merc",
	"946": "silvia",
	"947": "snow",
	"948": "snow_djt",
	"949": "s_field",
	"950": "swmagic",
	"951": "savage",
	"952": "switch",
	"953": "switchcs",
	"954": "t_roast",
	"955": "t_mysprt",
	"956": "trcsr_cs",
	"957": "traces_r",
	"958": "twodays",
	"959": "ugotta_r",
	"960": "wannatel",
	"961": "yourbody",
	"962": "_lion",
	"963": "_showa",
	"964": "_manatsu",
	"966": "savagecp",
	"967": "atmcag26",
	"968": "fun30",
	"969": "parasv31",
	"970": "advanc32"
}